friendly_captcha_client/__init__.py
friendly_captcha_client/client.py
friendly_captcha_client-0.1.0.dist-info/LICENSE
friendly_captcha_client-0.1.0.dist-info/METADATA
friendly_captcha_client-0.1.0.dist-info/WHEEL
friendly_captcha_client-0.1.0.dist-info/RECORD
