Metadata-Version: 2.1
Name: friendly-captcha-client
Version: 0.1.0
Summary: A client for Friendly Captcha.
Home-page: https://developer.friendlycaptcha.com/
Keywords: Friendly Captcha Client,Captcha
Author: Antal Nagy
Author-email: dev@friendlycaptcha.com
Requires-Python: >=3.6,<4.0
Classifier: Programming Language :: Python :: 3
Classifier: Programming Language :: Python :: 3.6
Classifier: Programming Language :: Python :: 3.7
Classifier: Programming Language :: Python :: 3.8
Classifier: Programming Language :: Python :: 3.9
Classifier: Programming Language :: Python :: 3.10
Classifier: Programming Language :: Python :: 3.11
Classifier: Programming Language :: Python :: 3.12
Classifier: Programming Language :: Python :: 3.13
Requires-Dist: pydantic (==2.1.1)
Requires-Dist: requests (==2.31.0)
Project-URL: Repository, https://github.com/FriendlyCaptcha/friendly-captcha-python
